[
    {
        "name": "Link Wray - Rumble - (backing track)",
        "full_name": "55z6yXP0trg - duration={{164}} - Link Wray - Rumble - (backing track).mp3",
        "url": "https://drive.google.com/uc?id=1jHlECSqdqWt4mlY9cPfCHnUYPp-DFJ3I&export=download"
    },
    {
        "name": "Rush \u2014 Working Man (Vault Edition), bass & drum tracks only",
        "full_name": "EWDG4UDb00I - duration={{421}} - Rush \u2014 Working Man (Vault Edition), bass & drum tracks only.mp3",
        "url": "https://drive.google.com/uc?id=1TyKq8R27Q1bIy-SN3i-QmjLk_nxMBMJq&export=download"
    },
    {
        "name": "Rush - Working Man (Bass & Drums)",
        "full_name": "frdwrEDweFA - duration={{421}} - Rush - Working Man (Bass & Drums).mp3",
        "url": "https://drive.google.com/uc?id=17cRQe6WrxcDp7eNDC74-j4lQ4eD_XXna&export=download"
    },
    {
        "name": "Autumn leaves _ Les feuilles mortes (120 bpm)  - Backing track",
        "full_name": "Xjf2kiDO19Y - duration={{387}} - Autumn leaves _ Les feuilles mortes (120 bpm)  - Backing track.mp3",
        "url": "https://drive.google.com/uc?id=1xTjAv4sLOBRqAY-UrlgkrOKN52AGOCbx&export=download"
    },
    {
        "name": "Djavan   Flor de Lis   Backingtrack",
        "full_name": "0MNxHBIQs8w - duration={{226}} - Djavan   Flor de Lis   Backingtrack.mp3",
        "url": "https://drive.google.com/uc?id=1JHXIYymmqNqvYzh6UTViJI4FCb-SpVv7&export=download"
    },
    {
        "name": "Fly me to the moon  - Backing Track",
        "full_name": "8H_5GcUxMHM - duration={{341}} - Fly me to the moon  - Backing Track.mp3",
        "url": "https://drive.google.com/uc?id=1FKGEC-oxE7t9QvKi-tghJDpOCkShiRFO&export=download"
    },
    {
        "name": "KARAOKE Encontros e Despedidas - Maria Rita",
        "full_name": "wo4X5EMeFr0 - duration={{256}} - KARAOKE Encontros e Despedidas - Maria Rita.mp3",
        "url": "https://drive.google.com/uc?id=1EsaeJcCcHVA8Izb0REiF0zeiWrkdEwIE&export=download"
    },
    {
        "name": "Rhythm Changes (Bb) - (Gypsy Jazz) Backing Track",
        "full_name": "a1QpnYmFWhU - duration={{804}} - Rhythm Changes (Bb) - (Gypsy Jazz) Backing Track.mp3",
        "url": "https://drive.google.com/uc?id=1q95XSKDWbTM9MKfoyqKwtKNLizufdkrR&export=download"
    },
    {
        "name": "Stella By Starlight 200bpm",
        "full_name": "kIeP29M-qts - duration={{242}} - Stella By Starlight 200bpm.mp3",
        "url": "https://drive.google.com/uc?id=15azn8CmFJk9dWOyS4iiQtBMYPK0tdRut&export=download"
    },
    {
        "name": "\u3010Spain\u3011Backing Track BPM=135 (Score Original BPM)",
        "full_name": "tZo2tORlskI - duration={{301}} - \u3010Spain\u3011Backing Track BPM=135 (Score Original BPM).mp3",
        "url": "https://drive.google.com/uc?id=1ykSKPpDFjQJ1AD03gSsoAomtJDvmp8zZ&export=download"
    },
    {
        "name": "Bossa Nova (Brigas nunca mais) - Vers\u00e3o para Viol\u00e3o",
        "full_name": "xirFUyxXXVk - duration={{120}} - Bossa Nova (Brigas nunca mais) - Vers\u00e3o para Viol\u00e3o.mp3",
        "url": "https://drive.google.com/uc?id=1dBdMuwudp3OFO4fRYkDoWUf_1zbBo-5a&export=download"
    },
    {
        "name": "The Look Of Love (Bacharach)- Backing + music sheet",
        "full_name": "Mp4w8oWwDwk - duration={{353}} - The Look Of Love (Bacharach)- Backing + music sheet.mp3",
        "url": "https://drive.google.com/uc?id=1dC0rH8PTWsO20YlwfolYb2vtbPduyjUb&export=download"
    },
    {
        "name": "ESTATE Backing Track",
        "full_name": "ITW4UAF3mgk - duration={{366}} - ESTATE Backing Track.mp3",
        "url": "https://drive.google.com/uc?id=1rbDbDYLjG8fMt5pDdCWLD_US8KTCLRyj&export=download"
    },
    {
        "name": "Flintstone's theme  Play along - Backing track (C key score guitar_piano_flute)",
        "full_name": "kA-NUXgCR20 - duration={{149}} - Flintstone's theme  Play along - Backing track (C key score guitar_piano_flute).mp3",
        "url": "https://drive.google.com/uc?id=1d0XniiHDVTGgZ3yXo_JKK4iZ39uOWkkq&export=download"
    },
    {
        "name": "Stella by Starlight  - Play along - Backing track (Bb key score trumpet_tenor sax_clarinet)",
        "full_name": "j1ooF1nL5tY - duration={{250}} - Stella by Starlight  - Play along - Backing track (Bb key score trumpet_tenor sax_clarinet).mp3",
        "url": "https://drive.google.com/uc?id=1iIi8dMG9Je4Uw5ff9E9rXrJX14ZpTYeu&export=download"
    }
]